zulip/__init__.py
zulip/send.py
zulip_beta-0.2.5.data/data/share/zulip/examples/create-user
zulip_beta-0.2.5.data/data/share/zulip/examples/edit-message
zulip_beta-0.2.5.data/data/share/zulip/examples/get-presence
zulip_beta-0.2.5.data/data/share/zulip/examples/get-public-streams
zulip_beta-0.2.5.data/data/share/zulip/examples/list-members
zulip_beta-0.2.5.data/data/share/zulip/examples/list-subscriptions
zulip_beta-0.2.5.data/data/share/zulip/examples/print-events
zulip_beta-0.2.5.data/data/share/zulip/examples/print-messages
zulip_beta-0.2.5.data/data/share/zulip/examples/recent-messages
zulip_beta-0.2.5.data/data/share/zulip/examples/send-message
zulip_beta-0.2.5.data/data/share/zulip/examples/subscribe
zulip_beta-0.2.5.data/data/share/zulip/examples/unsubscribe
zulip_beta-0.2.5.data/data/share/zulip/examples/zuliprc
zulip_beta-0.2.5.data/data/share/zulip/integrations/basecamp/zulip_basecamp_config.py
zulip_beta-0.2.5.data/data/share/zulip/integrations/basecamp/zulip_basecamp_mirror
zulip_beta-0.2.5.data/data/share/zulip/integrations/codebase/zulip_codebase_config.py
zulip_beta-0.2.5.data/data/share/zulip/integrations/codebase/zulip_codebase_mirror
zulip_beta-0.2.5.data/data/share/zulip/integrations/git/post-receive
zulip_beta-0.2.5.data/data/share/zulip/integrations/git/zulip_git_config.py
zulip_beta-0.2.5.data/data/share/zulip/integrations/google/get-google-credentials
zulip_beta-0.2.5.data/data/share/zulip/integrations/google/google-calendar
zulip_beta-0.2.5.data/data/share/zulip/integrations/hg/zulip-changegroup.py
zulip_beta-0.2.5.data/data/share/zulip/integrations/jira/org/humbug/jira/ZulipListener.groovy
zulip_beta-0.2.5.data/data/share/zulip/integrations/nagios/nagios-notify-zulip
zulip_beta-0.2.5.data/data/share/zulip/integrations/nagios/zulip_nagios.cfg
zulip_beta-0.2.5.data/data/share/zulip/integrations/nagios/zuliprc.example
zulip_beta-0.2.5.data/data/share/zulip/integrations/openshift/post_deploy
zulip_beta-0.2.5.dist-info/DESCRIPTION.rst
zulip_beta-0.2.5.dist-info/METADATA
zulip_beta-0.2.5.dist-info/RECORD
zulip_beta-0.2.5.dist-info/WHEEL
zulip_beta-0.2.5.dist-info/entry_points.txt
zulip_beta-0.2.5.dist-info/metadata.json
zulip_beta-0.2.5.dist-info/top_level.txt
