Metadata-Version: 2.0
Name: zulip-beta
Version: 0.2.5
Summary: Bindings for the Zulip message API
Home-page: https://www.zulip.org/dist/api/
Author: Zulip Open Source Project
Author-email: zulip-devel@googlegroups.com
License: UNKNOWN
Platform: UNKNOWN
Classifier: Development Status :: 3 - Alpha
Classifier: Environment :: Web Environment
Classifier: Intended Audience :: Developers
Classifier: License :: OSI Approved :: MIT License
Classifier: Topic :: Communications :: Chat
Requires-Dist: requests (>=0.12.1)
Requires-Dist: simplejson
Requires-Dist: six
Requires-Dist: typing (>=3.5.2.2)
